oven/__init__.py
oven/cli.py
oven/consts.py
oven/oven.py
oven/progress.py
oven/version.py
oven/backends/__init__.py
oven/backends/api/__init__.py
oven/backends/api/info.py
oven/backends/dingtalk/__init__.py
oven/backends/dingtalk/info.py
oven/backends/email/__init__.py
oven/backends/email/info.py
oven/backends/feishu/__init__.py
oven/backends/feishu/info.py
oven/backends/slack/__init__.py
oven/backends/slack/info.py
oven/utils/__init__.py
oven/utils/cfg.py
oven/utils/manual.txt
oven/utils/time.py
oven/utils/version.py
exp_oven-0.6.2.dist-info/LICENSE
exp_oven-0.6.2.dist-info/METADATA
exp_oven-0.6.2.dist-info/WHEEL
exp_oven-0.6.2.dist-info/entry_points.txt
exp_oven-0.6.2.dist-info/top_level.txt
exp_oven-0.6.2.dist-info/RECORD
