Metadata-Version: 2.1
Name: exp_oven
Version: 0.6.2
Summary: Experiments monitor and notification utilities.
Author: Yan XIA
Author-email: 
Classifier: Programming Language :: Python :: 3
Classifier: License :: OSI Approved :: MIT License
Classifier: Operating System :: OS Independent
Requires-Python: >=3.8
License-File: LICENSE
Requires-Dist: omegaconf
Requires-Dist: requests
